{
  "title": "Developer Changelog",
  "items": [
    {
      "title": "Hello Ethereum Wallets!",
      "permalink": "/zh-CN/blog/hello-ethereum-wallets",
      "unlisted": false,
      "date": "2024-11-07T00:00:00.000Z"
    },
    {
      "title": "Future of Pagoda Services",
      "permalink": "/zh-CN/blog/2024-08-13-pagoda-services",
      "unlisted": false,
      "date": "2024-08-13T00:00:00.000Z"
    },
    {
      "title": "An update on the near.org / RPC outage on July 11, 2024",
      "permalink": "/zh-CN/blog/2024-07-11-near-org-outage",
      "unlisted": false,
      "date": "2024-07-18T00:00:00.000Z"
    },
    {
      "title": "Pagoda Pauses the B.O.S. Web Engine R&D Project",
      "permalink": "/zh-CN/blog/bos-web-engine-sunset",
      "unlisted": false,
      "date": "2024-07-01T00:00:00.000Z"
    },
    {
      "title": "One place for all Smart Contracts Docs",
      "permalink": "/zh-CN/blog/sdks-unified",
      "unlisted": false,
      "date": "2024-06-28T00:00:00.000Z"
    },
    {
      "title": "Getting Started on NEAR Using Windows",
      "permalink": "/zh-CN/blog/getting-started-on-windows",
      "unlisted": false,
      "date": "2024-06-05T00:00:00.000Z"
    },
    {
      "title": "It's gonna be Legen... wait for it...",
      "permalink": "/zh-CN/blog/yield-resume",
      "unlisted": false,
      "date": "2024-05-30T00:00:00.000Z"
    },
    {
      "title": "Use cases for Chain Signatures",
      "permalink": "/zh-CN/blog/chain-signatures-use-cases",
      "unlisted": false,
      "date": "2024-05-15T00:00:00.000Z"
    },
    {
      "title": "Reorganizing our docs",
      "permalink": "/zh-CN/blog/reorganizing-docs",
      "unlisted": false,
      "date": "2024-04-24T00:00:00.000Z"
    },
    {
      "title": "We have a blog now!",
      "permalink": "/zh-CN/blog/we-have-a-blog",
      "unlisted": false,
      "date": "2024-04-23T00:00:00.000Z"
    }
  ]
}