{
  "id": "build/near-components/bos-gateway",
  "title": "Using components on WebApps",
  "description": "In order to use the components you create in a WebApp you need to use what is known as the NEAR VM. This virtual machine helps you to easily fetch components from the blockchain and transform them into executable code.",
  "source": "@site/i18n/zh-CN/docusaurus-plugin-content-docs/current/2.build/3.near-components/bos-gateway.md",
  "sourceDirName": "2.build/3.near-components",
  "slug": "/build/near-components/bos-gateway",
  "permalink": "/zh-CN/build/near-components/bos-gateway",
  "draft": false,
  "unlisted": false,
  "editUrl": "https://github.com/near/docs/edit/master/website/../docs/2.build/3.near-components/bos-gateway.md",
  "tags": [],
  "version": "current",
  "lastUpdatedBy": "Github Actions",
  "lastUpdatedAt": 1712954223000,
  "frontMatter": {
    "id": "bos-gateway",
    "title": "Using components on WebApps"
  },
  "sidebar": "build",
  "previous": {
    "title": "Handling Historical data",
    "permalink": "/zh-CN/build/near-components/anatomy/bos-components"
  },
  "next": {
    "title": "What are Web3 Apps?",
    "permalink": "/zh-CN/build/web3-apps/what-is"
  }
}