{
  "id": "bos/components/ipfs",
  "title": "Image Uploader",
  "description": "The IpfsImageUpload is a built-in component that enables users to directly upload an image to the InterPlanetary File System (IPFS).",
  "source": "@site/../docs/bos/components/ipfsimageupload.md",
  "sourceDirName": "bos/components",
  "slug": "/bos/components/ipfs",
  "permalink": "/bos/components/ipfs",
  "draft": false,
  "unlisted": false,
  "editUrl": "https://github.com/near/docs/edit/master/website/../docs/bos/components/ipfsimageupload.md",
  "tags": [],
  "version": "current",
  "lastUpdatedBy": "Damián Parrino",
  "lastUpdatedAt": 1682457647,
  "formattedLastUpdatedAt": "Apr 25, 2023",
  "frontMatter": {
    "id": "ipfs",
    "title": "Image Uploader"
  },
  "sidebar": "integrate",
  "previous": {
    "title": "Widget",
    "permalink": "/bos/components/widgets"
  },
  "next": {
    "title": "Files",
    "permalink": "/bos/components/files"
  }
}