{
  "id": "build/smart-contracts/security/sybil",
  "title": "시빌 공격",
  "description": "스마트 컨트랙트를 개발 중에 있다면, 개인이 여러 NEAR 계정을 만들 수 있다는 점을 염두에 두시기 바랍니다. 이것은 특히 DAO와 같이 다수의 결정과 관련된 생태계와 관련이 있습니다.",
  "source": "@site/i18n/ko/docusaurus-plugin-content-docs/current/2.build/2.smart-contracts/security/sybil.md",
  "sourceDirName": "2.build/2.smart-contracts/security",
  "slug": "/build/smart-contracts/security/sybil",
  "permalink": "/ko/build/smart-contracts/security/sybil",
  "draft": false,
  "unlisted": false,
  "editUrl": "https://github.com/near/docs/edit/master/website/../docs/2.build/2.smart-contracts/security/sybil.md",
  "tags": [],
  "version": "current",
  "lastUpdatedBy": "Github Actions",
  "lastUpdatedAt": 1712954223000,
  "frontMatter": {
    "id": "sybil",
    "title": "시빌 공격"
  },
  "sidebar": "build",
  "previous": {
    "title": "사용자가 맞는지 확인 (1yⓃ)",
    "permalink": "/ko/build/smart-contracts/security/one-yocto"
  },
  "next": {
    "title": "프론트러닝",
    "permalink": "/ko/build/smart-contracts/security/frontrunning"
  }
}