{
  "id": "tutorials/examples/donation",
  "title": "기부",
  "description": "Our donation example enables to forward NEAR Tokens to an account while keeping track of it. It is one of the simplest examples on making a contract handle tranfers.",
  "source": "@site/i18n/ko/docusaurus-plugin-content-docs/current/3.tutorials/examples/donation.md",
  "sourceDirName": "3.tutorials/examples",
  "slug": "/tutorials/examples/donation",
  "permalink": "/ko/tutorials/examples/donation",
  "draft": false,
  "unlisted": false,
  "editUrl": "https://github.com/near/docs/edit/master/website/../docs/3.tutorials/examples/donation.md",
  "tags": [],
  "version": "current",
  "lastUpdatedBy": "Github Actions",
  "lastUpdatedAt": 1712954223000,
  "frontMatter": {
    "id": "donation",
    "title": "기부"
  },
  "sidebar": "tutorials",
  "previous": {
    "title": "방명록",
    "permalink": "/ko/tutorials/examples/guest-book"
  },
  "next": {
    "title": "교차 컨트랙트 호출(Cross Contract Call)",
    "permalink": "/ko/tutorials/examples/xcc"
  }
}