{
  "id": "bos/tutorial/lido",
  "title": "Lido 예시",
  "description": "If you are ready to explore further, the Lido component serves as an excellent fully-fledged example, as it demonstrates how to interact with a smart contract deployed on the Ethereum mainnet.",
  "source": "@site/i18n/ko/docusaurus-plugin-content-docs/current/bos/tutorial/hello-lido.md",
  "sourceDirName": "bos/tutorial",
  "slug": "/bos/tutorial/lido",
  "permalink": "/ko/bos/tutorial/lido",
  "draft": false,
  "unlisted": false,
  "editUrl": "https://github.com/near/docs/edit/master/website/../docs/bos/tutorial/hello-lido.md",
  "tags": [],
  "version": "current",
  "lastUpdatedBy": "Github Actions",
  "lastUpdatedAt": 1709152665,
  "formattedLastUpdatedAt": "2024년 2월 28일",
  "frontMatter": {
    "id": "lido",
    "title": "Lido 예시"
  },
  "sidebar": "tutorials",
  "previous": {
    "title": "Best Practices for Ethereum developers on NEAR",
    "permalink": "/ko/bos/tutorial/ethers-js-best-practices"
  },
  "next": {
    "title": "소개",
    "permalink": "/ko/tutorials/fts/introduction"
  }
}