{
  "id": "tutorials/fts/defining-a-token",
  "title": "Defining a Fungible Token",
  "description": "This is the first of many tutorials in a series where you'll be creating a complete FT smart contract from scratch that conforms with all the NEAR FT standards. Today you'll learn what a Fungible Token is and how you can define one on the NEAR blockchain. You will be modifying a bare-bones skeleton smart contract by filling in the necessary code snippets needed to add this functionality.",
  "source": "@site/i18n/zh-CN/docusaurus-plugin-content-docs/current/3.tutorials/fts/2-define-a-token.md",
  "sourceDirName": "3.tutorials/fts",
  "slug": "/tutorials/fts/defining-a-token",
  "permalink": "/zh-CN/tutorials/fts/defining-a-token",
  "draft": false,
  "unlisted": false,
  "editUrl": "https://github.com/near/docs/edit/master/website/../docs/3.tutorials/fts/2-define-a-token.md",
  "tags": [],
  "version": "current",
  "lastUpdatedBy": "Github Actions",
  "lastUpdatedAt": 1705914809,
  "formattedLastUpdatedAt": "2024年1月22日",
  "sidebarPosition": 2,
  "frontMatter": {
    "id": "defining-a-token",
    "title": "Defining a Fungible Token",
    "sidebar_label": "Defining Your Token"
  },
  "sidebar": "tutorials",
  "previous": {
    "title": "Contract Architecture",
    "permalink": "/zh-CN/tutorials/fts/skeleton"
  },
  "next": {
    "title": "Circulating Supply",
    "permalink": "/zh-CN/tutorials/fts/circulating-supply"
  }
}