{
  "id": "data-availability/integrations",
  "title": "Integrations",
  "description": "We have some proof of concept works for integrating with rollups. We are working to prove the system's capabilities and provide a reference implementation for others to follow.",
  "source": "@site/i18n/ko/docusaurus-plugin-content-docs/current/data-availability/integrations.md",
  "sourceDirName": "data-availability",
  "slug": "/data-availability/integrations",
  "permalink": "/ko/data-availability/integrations",
  "draft": false,
  "unlisted": false,
  "editUrl": "https://github.com/near/docs/edit/master/website/../docs/data-availability/integrations.md",
  "tags": [],
  "version": "current",
  "lastUpdatedBy": "Github Actions",
  "lastUpdatedAt": 1704996595,
  "formattedLastUpdatedAt": "2024년 1월 11일",
  "frontMatter": {
    "id": "integrations",
    "title": "Integrations"
  },
  "sidebar": "data-availability",
  "previous": {
    "title": "RPC Client",
    "permalink": "/ko/data-availability/rpc"
  },
  "next": {
    "title": "Optimism",
    "permalink": "/ko/data-availability/optimism"
  }
}