{
  "id": "api/rpc/access-keys",
  "title": "Access Keys",
  "description": "The RPC API enables you to retrieve information about an account's access keys.",
  "source": "@site/i18n/zh-CN/docusaurus-plugin-content-docs/current/5.api/rpc/access-keys.md",
  "sourceDirName": "5.api/rpc",
  "slug": "/api/rpc/access-keys",
  "permalink": "/zh-CN/api/rpc/access-keys",
  "draft": false,
  "unlisted": false,
  "editUrl": "https://github.com/near/docs/edit/master/website/../docs/5.api/rpc/access-keys.md",
  "tags": [],
  "version": "current",
  "lastUpdatedBy": "Github Actions",
  "lastUpdatedAt": 1718378911000,
  "frontMatter": {
    "id": "access-keys",
    "title": "Access Keys"
  },
  "sidebar": "api",
  "previous": {
    "title": "Setup",
    "permalink": "/zh-CN/api/rpc/setup"
  },
  "next": {
    "title": "Accounts / Contracts",
    "permalink": "/zh-CN/api/rpc/contracts"
  }
}