{
  "app.js": "/static/js/app.eb97cab2.js",
  "app.js.map": "/static/js/app.9c8bf5948adb60ec1616.js.map",
  "runtime~app.js": "/static/js/runtime~app.9c8bf5948adb60ec1616.js",
  "runtime~app.js.map": "/static/js/runtime~app.9c8bf5948adb60ec1616.js.map",
  "src-basics-technical-faq.js": "/static/js/src-basics-technical-faq.0e0391b2.js",
  "src-basics-technical-faq.js.map": "/static/js/src-basics-technical-faq.9c8bf5948adb60ec1616.js.map",
  "src-basics-the-basics.js": "/static/js/src-basics-the-basics.c2bd9981.js",
  "src-basics-the-basics.js.map": "/static/js/src-basics-the-basics.9c8bf5948adb60ec1616.js.map",
  "src-index.js": "/static/js/src-index.6e7dc375.js",
  "src-index.js.map": "/static/js/src-index.9c8bf5948adb60ec1616.js.map",
  "src-lib-js.js": "/static/js/src-lib-js.6f89b81c.js",
  "src-lib-js.js.map": "/static/js/src-lib-js.9c8bf5948adb60ec1616.js.map",
  "src-lib-ts.js": "/static/js/src-lib-ts.1da9b484.js",
  "src-lib-ts.js.map": "/static/js/src-lib-ts.9c8bf5948adb60ec1616.js.map",
  "src-protocol-consensus.js": "/static/js/src-protocol-consensus.cd53306e.js",
  "src-protocol-consensus.js.map": "/static/js/src-protocol-consensus.9c8bf5948adb60ec1616.js.map",
  "src-quick-start.js": "/static/js/src-quick-start.1aece4d1.js",
  "src-quick-start.js.map": "/static/js/src-quick-start.9c8bf5948adb60ec1616.js.map",
  "src-tutorials-multiplayergame.js": "/static/js/src-tutorials-multiplayergame.2d0a3a4f.js",
  "src-tutorials-multiplayergame.js.map": "/static/js/src-tutorials-multiplayergame.9c8bf5948adb60ec1616.js.map",
  "src-tutorials-oracle.js": "/static/js/src-tutorials-oracle.ccf8364e.js",
  "src-tutorials-oracle.js.map": "/static/js/src-tutorials-oracle.9c8bf5948adb60ec1616.js.map",
  "src-tutorials-token.js": "/static/js/src-tutorials-token.b278d1ab.js",
  "src-tutorials-token.js.map": "/static/js/src-tutorials-token.9c8bf5948adb60ec1616.js.map",
  "vendors.js": "/static/js/vendors.ed70be1a.js",
  "vendors.js.map": "/static/js/vendors.9c8bf5948adb60ec1616.js.map",
  "static/js/13.ad96fd7d.js": "/static/js/13.ad96fd7d.js",
  "static/js/13.9c8bf5948adb60ec1616.js.map": "/static/js/13.9c8bf5948adb60ec1616.js.map",
  "index.html": "/index.html"
}