{
  "app.js": "/static/js/app.a8a0b247.js",
  "app.js.map": "/static/js/app.2c058590990824f8f0c7.js.map",
  "runtime~app.js": "/static/js/runtime~app.2c058590990824f8f0c7.js",
  "runtime~app.js.map": "/static/js/runtime~app.2c058590990824f8f0c7.js.map",
  "src-index.js": "/static/js/src-index.8a97908b.js",
  "src-index.js.map": "/static/js/src-index.2c058590990824f8f0c7.js.map",
  "src-lib-js.js": "/static/js/src-lib-js.5b2b2dd0.js",
  "src-lib-js.js.map": "/static/js/src-lib-js.2c058590990824f8f0c7.js.map",
  "src-protocol-consensus.js": "/static/js/src-protocol-consensus.96e5c6e0.js",
  "src-protocol-consensus.js.map": "/static/js/src-protocol-consensus.2c058590990824f8f0c7.js.map",
  "src-quick-start.js": "/static/js/src-quick-start.4d2d8815.js",
  "src-quick-start.js.map": "/static/js/src-quick-start.2c058590990824f8f0c7.js.map",
  "src-tutorials-multiplayergame.js": "/static/js/src-tutorials-multiplayergame.e012d193.js",
  "src-tutorials-multiplayergame.js.map": "/static/js/src-tutorials-multiplayergame.2c058590990824f8f0c7.js.map",
  "src-tutorials-oracle.js": "/static/js/src-tutorials-oracle.c8a0b384.js",
  "src-tutorials-oracle.js.map": "/static/js/src-tutorials-oracle.2c058590990824f8f0c7.js.map",
  "src-tutorials-token.js": "/static/js/src-tutorials-token.3403f097.js",
  "src-tutorials-token.js.map": "/static/js/src-tutorials-token.2c058590990824f8f0c7.js.map",
  "vendors.js": "/static/js/vendors.7b18bee5.js",
  "vendors.js.map": "/static/js/vendors.2c058590990824f8f0c7.js.map",
  "static/js/10.e5b6cee7.js": "/static/js/10.e5b6cee7.js",
  "static/js/10.2c058590990824f8f0c7.js.map": "/static/js/10.2c058590990824f8f0c7.js.map",
  "index.html": "/index.html"
}